ce2fs/__init__.py
ce2fs/__main__.py
ce2fs-0.1.2.dist-info/METADATA
ce2fs-0.1.2.dist-info/WHEEL
ce2fs-0.1.2.dist-info/entry_points.txt
ce2fs-0.1.2.dist-info/licenses/LICENSE
ce2fs-0.1.2.dist-info/RECORD
