Metadata-Version: 2.3
Name: ce2fs
Version: 0.1.2
Project-URL: Homepage, https://github.com/tremwil/ce2fs
Project-URL: Repository, https://github.com/tremwil/ce2fs.git
Project-URL: Issues, https://github.com/tremwil/issues
Author-email: William Tremblay <tremwil@gmail.com>
Maintainer-email: William Tremblay <tremwil@gmail.com>
License: MIT License
License-File: LICENSE
Keywords: Cheat Engine
Requires-Python: >=3.10
Requires-Dist: lxml>=5.2.2
